README.md
setup.py
diff_as_git/Differ.py
diff_as_git/__init__.py
diff_as_git/utilities.py
diff_as_git.egg-info/PKG-INFO
diff_as_git.egg-info/SOURCES.txt
diff_as_git.egg-info/dependency_links.txt
diff_as_git.egg-info/requires.txt
diff_as_git.egg-info/top_level.txt