Metadata-Version: 2.1
Name: diff-as-git
Version: 0.0.1
Summary: This lib is an implementation of the `git diff` tool in Python using the Myers Difference algorithm.
Home-page: UNKNOWN
Author: Lucas de Souza e Sousa
Author-email: lucas11souza97@gmail.com
License: MIT License
Keywords: DIff as git
Platform: UNKNOWN
